arrowverse_reorderer/__init__.py
arrowverse_reorderer/__main__.py
arrowverse_reorderer-2.5.0.dist-info/entry_points.txt
arrowverse_reorderer-2.5.0.dist-info/LICENSE
arrowverse_reorderer-2.5.0.dist-info/WHEEL
arrowverse_reorderer-2.5.0.dist-info/METADATA
arrowverse_reorderer-2.5.0.dist-info/RECORD
