Metadata-Version: 2.1
Name: arrowverse_reorderer
Version: 2.5.0
Summary: Order Arrowverse episodes files in air time order
Keywords: Arrowverse,Arrow,The Flash,Rename,Order
Author-email: Alberto Pasqualetto <39854348+albertopasqualetto@users.noreply.github.com>
Requires-Python: >=3.7
Classifier: Programming Language :: Python :: 3
Classifier: Environment :: Console
Classifier: License :: OSI Approved :: Apache Software License
Classifier: Operating System :: OS Independent
Classifier: Topic :: Desktop Environment :: File Managers
Classifier: Topic :: Utilities
Requires-Dist: mnamer>=2.5.4
Requires-Dist: requests>=2.27.1
Requires-Dist: beautifulsoup4>=4.11.1
Requires-Dist: lxml>=4.8.0
Requires-Dist: html5lib>=1.1
Requires-Dist: pandas>=1.4.3
Requires-Dist: filetype>=1.0.13
Project-URL: Bug Tracker, https://github.com/albertopasqualetto/Arrowverse-Reorderer/issues
Project-URL: Homepage, https://github.com/albertopasqualetto/Arrowverse-Reorderer
